README.md
setup.cfg
setup.py
afterdown/__init__.py
afterdown/__main__.py
afterdown.egg-info/PKG-INFO
afterdown.egg-info/SOURCES.txt
afterdown.egg-info/dependency_links.txt
afterdown.egg-info/entry_points.txt
afterdown.egg-info/requires.txt
afterdown.egg-info/top_level.txt
afterdown/core/__init__.py
afterdown/core/constants.py
afterdown/core/countersummary.py
afterdown/core/dropboxsync.py
afterdown/core/knownfiles.py
afterdown/core/matching.py
afterdown/core/rss.py
afterdown/core/rules.py
afterdown/core/season_info.py
afterdown/core/utils.py
afterdown/core/email/__init__.py
afterdown/core/email/log.py
afterdown/core/email/mail_report.py
afterdown/tests/__init__.py
afterdown/tests/test_dependency_resolver.py
afterdown/tests/test_dropbox.py
afterdown/tests/test_guessit.py
afterdown/tests/test_known.py
afterdown/tests/test_match_string.py
afterdown/tests/test_realtest.py
afterdown/tests/test_rss.py
afterdown/tests/test_rules.py
afterdown/tests/test_season_info.py
afterdown/tests/test_unicode_paths.py
afterdown/tests/playground/__init__.py
afterdown/tests/playground/create_files_from_ls.py