Metadata-Version: 1.1
Name: afterdown
Version: 0.9.93
Summary: Automate the organization of your downloads.
Home-page: https://github.com/dariosky/afterdown
Author: Dario Varotto
Author-email: dario.varotto@gmail.com
License: GPL2
Keywords: deployment webfaction cli letsencrypt certificate
Platform: UNKNOWN
Classifier: Development Status :: 4 - Beta
Classifier: Intended Audience :: Developers
Classifier: Topic :: System :: Software Distribution
Classifier: License :: OSI Approved :: GNU General Public License v2 (GPLv2)
Classifier: Programming Language :: Python :: 2
Classifier: Programming Language :: Python :: 2.6
Classifier: Programming Language :: Python :: 2.7
Classifier: Programming Language :: Python :: 3
Classifier: Programming Language :: Python :: 3.6
